cpu_controller_linux/__init__.py
cpu_controller_linux/cpu.png
cpu_controller_linux/main.py
cpu_controller_linux-0.1.0.dist-info/LICENSE
cpu_controller_linux-0.1.0.dist-info/METADATA
cpu_controller_linux-0.1.0.dist-info/WHEEL
cpu_controller_linux-0.1.0.dist-info/entry_points.txt
cpu_controller_linux-0.1.0.dist-info/top_level.txt
cpu_controller_linux-0.1.0.dist-info/RECORD
