Metadata-Version: 2.1
Name: cpu-controller-linux
Version: 0.1.0
Summary: Turn on/off CPU cores in Linux
Author: Devansh Arora
Author-email: hsnaved.reverse@gmail.com
Keywords: python,linux,cpu,battery life,cpu cores
Classifier: Intended Audience :: Developers
Classifier: Programming Language :: Python :: 3
Classifier: Operating System :: Unix
License-File: LICENSE
Requires-Dist: PyQt6
